{
  "slug": "hyundai",
  "ticker": "005380",
  "name_ko": "현대차",
  "name_en": "Hyundai Motor",
  "updated_at": "2026-07-23T19:17:23.637+09:00",
  "source": "naver_finance_frgn",
  "note": "추정 매매대금 = 종가 × 순매매량 (±5% 정확도)",
  "daily": [
    {
      "date": "2026-07-16",
      "foreign_won": 43498750000,
      "institutional_won": -26755875000
    },
    {
      "date": "2026-07-20",
      "foreign_won": -35265615000,
      "institutional_won": 41584977000
    },
    {
      "date": "2026-07-21",
      "foreign_won": -16380546000,
      "institutional_won": -5743605000
    },
    {
      "date": "2026-07-22",
      "foreign_won": 45001044000,
      "institutional_won": 11406802000
    },
    {
      "date": "2026-07-23",
      "foreign_won": 20812464000,
      "institutional_won": -16113168000
    }
  ],
  "cumulative_5d": {
    "foreign_won": 57666097000,
    "institutional_won": 4379131000,
    "retail_won": -62045228000
  }
}
