{
  "category": "hynix",
  "updated_at": "2026-05-20T12:02:55.821Z",
  "count": 5,
  "items": [
    {
      "title": "지방도 반도체·방산 특수…창원·청주 매매 50% 급증",
      "link": "https://www.hankyung.com/article/202605208235i",
      "source": "한국경제",
      "ts": 1779269402000,
      "pub": "Wed, 20 May 2026 18:30:02 +0900"
    },
    {
      "title": "\"SK하이닉스가 쓴다\"…링글, 반도체업계 영어교육 플랫폼 입지↑",
      "link": "https://www.mt.co.kr/future/2026/05/20/2026052015452824031",
      "source": "머니투데이",
      "ts": 1779269400000,
      "pub": "Wed, 20 May 2026 18:30:00 +0900"
    },
    {
      "title": "반도체주 과매수 신호…엔비디아, 호실적에도 주가 하락했는데 이번엔?[오미주]",
      "link": "https://www.mt.co.kr/world/2026/05/20/2026052015073123146",
      "source": "머니투데이",
      "ts": 1779267900000,
      "pub": "Wed, 20 May 2026 18:05:00 +0900"
    },
    {
      "title": "\"목표는 엔비디아 생태계 구축\"…젠슨 황, 135조원 뿌려",
      "link": "https://www.yna.co.kr/view/AKR20260520137800009",
      "source": "연합뉴스 국제",
      "ts": 1779260871000,
      "pub": "Wed, 20 May 2026 16:07:51 +0900"
    },
    {
      "title": "삼전·하닉에 도전…中 양대 메모리업체 IPO 준비 잰걸음",
      "link": "https://www.yna.co.kr/view/AKR20260520076300009",
      "source": "연합뉴스 국제",
      "ts": 1779243488000,
      "pub": "Wed, 20 May 2026 11:18:08 +0900"
    }
  ]
}