{
  "category": "hynix",
  "updated_at": "2026-07-04T01:48:28.266Z",
  "count": 7,
  "items": [
    {
      "title": "\"반도체 초호황이 '신의 축복'이라니\"…장관 발언에 '부글부글' [청와대는 지금]",
      "link": "https://www.hankyung.com/article/202607021576i",
      "source": "한국경제",
      "ts": 1783128095000,
      "pub": "Sat, 04 Jul 2026 10:21:35 +0900",
      "sentiment": "neutral"
    },
    {
      "title": "반도체 대장주도 맥 못추는데…\"이 실적에 너무 싸\" 30% '쑥'[김근희의 증시랩업]",
      "link": "https://www.mt.co.kr/stock/2026/07/04/2026070315255333110",
      "source": "머니투데이",
      "ts": 1783113120000,
      "pub": "Sat, 04 Jul 2026 06:12:00 +0900",
      "sentiment": "neutral"
    },
    {
      "title": "미래에셋, 1조3천억 자금조달 추진…'큰 손' 된 SK하이닉스",
      "link": "https://www.yna.co.kr/view/AKR20260703151000008",
      "source": "연합뉴스 경제",
      "ts": 1783073928000,
      "pub": "Fri, 3 Jul 2026 19:18:48 +0900",
      "sentiment": "neutral"
    },
    {
      "title": "서남충청권에 반도체, 영남권은 피지컬AI·우주…산업지도 재편",
      "link": "https://www.yna.co.kr/view/AKR20260703129200003",
      "source": "연합뉴스 경제",
      "ts": 1783066118000,
      "pub": "Fri, 3 Jul 2026 17:08:38 +0900",
      "sentiment": "neutral"
    },
    {
      "title": "키옥시아, 차세대 낸드플래시 출하…\"생산능력 확충\"",
      "link": "https://www.yna.co.kr/view/AKR20260703116400073",
      "source": "연합뉴스 국제",
      "ts": 1783061833000,
      "pub": "Fri, 3 Jul 2026 15:57:13 +0900",
      "sentiment": "neutral"
    },
    {
      "title": "\"2분기 메모리 시장규모 350조원…내년 하반기 상승세 둔화\"",
      "link": "https://www.yna.co.kr/view/AKR20260703105100003",
      "source": "연합뉴스 경제",
      "ts": 1783060145000,
      "pub": "Fri, 3 Jul 2026 15:29:05 +0900",
      "sentiment": "positive"
    },
    {
      "title": "KB證, SK하이닉스 목표가 420만원으로 상향…영업익 추정치↑",
      "link": "https://www.yna.co.kr/view/AKR20260703073600008",
      "source": "연합뉴스 경제",
      "ts": 1783047624000,
      "pub": "Fri, 3 Jul 2026 12:00:24 +0900",
      "sentiment": "neutral"
    }
  ]
}