{
  "category": "hynix",
  "updated_at": "2026-07-02T06:28:44.527Z",
  "count": 18,
  "items": [
    {
      "title": "당 복귀한 김민석, 첫 지역 일정 '청주 육거리시장·SK하이닉스 찾은 이유",
      "link": "https://www.mt.co.kr/politics/2026/07/02/2026070213403748374",
      "source": "머니투데이",
      "ts": 1782971794000,
      "pub": "Thu, 02 Jul 2026 14:56:34 +0900",
      "sentiment": "neutral"
    },
    {
      "title": "AI붐 타고 中반도체, IPO 러시…\"빠르게 자금 확보해 생산 확대\"",
      "link": "https://www.yna.co.kr/view/AKR20260702112800009",
      "source": "연합뉴스 국제",
      "ts": 1782971475000,
      "pub": "Thu, 2 Jul 2026 14:51:15 +0900",
      "sentiment": "neutral"
    },
    {
      "title": "\"반도체 급락하면 여기로 피신하라\"…'이곳'은 일제히 강세",
      "link": "https://www.hankyung.com/article/202607022116i",
      "source": "한국경제",
      "ts": 1782970995000,
      "pub": "Thu, 02 Jul 2026 14:43:15 +0900",
      "sentiment": "negative"
    },
    {
      "title": "AI·반도체 훈풍 타고 '체질전환'…대동금속 \"올해 수주 1000억 자신\"",
      "link": "https://www.mt.co.kr/living/2026/07/02/2026070213213080001",
      "source": "머니투데이",
      "ts": 1782970866000,
      "pub": "Thu, 02 Jul 2026 14:41:06 +0900",
      "sentiment": "positive"
    },
    {
      "title": "곽동신 한미반도체 회장, 50억 자사주 추가 매입…3년간 695억원어치 사들여",
      "link": "https://www.hankyung.com/article/202607022128i",
      "source": "한국경제",
      "ts": 1782970768000,
      "pub": "Thu, 02 Jul 2026 14:39:28 +0900",
      "sentiment": "neutral"
    },
    {
      "title": "파라텍, 반도체·배터리 공장 이어 바이오 플랜트 수주…소방 시장 독주",
      "link": "https://www.mt.co.kr/stock/2026/07/02/2026070213455681293",
      "source": "머니투데이",
      "ts": 1782970655000,
      "pub": "Thu, 02 Jul 2026 14:37:35 +0900",
      "sentiment": "positive"
    },
    {
      "title": "반도체팹 호재 터진 광주에 '챔피언스시티' 3216가구 분양",
      "link": "https://www.hankyung.com/article/202607022083i",
      "source": "한국경제",
      "ts": 1782970130000,
      "pub": "Thu, 02 Jul 2026 14:28:50 +0900",
      "sentiment": "neutral"
    },
    {
      "title": "'고점판독기' 미자, 주식 1억 손해 \"하이닉스 몰빵 후 신고가\"",
      "link": "https://www.hankyung.com/article/202607022016H",
      "source": "한국경제",
      "ts": 1782969847000,
      "pub": "Thu, 02 Jul 2026 14:24:07 +0900",
      "sentiment": "positive"
    },
    {
      "title": "노동부, '삼성·SK 메가 투자' 맞춰 반도체 인력 양성 논의",
      "link": "https://www.yna.co.kr/view/AKR20260702073700530",
      "source": "연합뉴스 경제",
      "ts": 1782968413000,
      "pub": "Thu, 2 Jul 2026 14:00:13 +0900",
      "sentiment": "neutral"
    },
    {
      "title": "서울 집값 상승률 소폭둔화…'반도체벨트' 강세 여전",
      "link": "https://www.hankyung.com/article/202607021604i",
      "source": "한국경제",
      "ts": 1782968408000,
      "pub": "Thu, 02 Jul 2026 14:00:08 +0900",
      "sentiment": "neutral"
    },
    {
      "title": "하반기 산업기상도…배터리·반도체 '맑음' 석유화학 '비'",
      "link": "https://www.yna.co.kr/view/AKR20260702029000003",
      "source": "연합뉴스 경제",
      "ts": 1782961207000,
      "pub": "Thu, 2 Jul 2026 12:00:07 +0900",
      "sentiment": "neutral"
    },
    {
      "title": "美 마이크로 원자로, 엔비디아 블랙웰 구동 시연 성공",
      "link": "https://www.yna.co.kr/view/AKR20260702078600009",
      "source": "연합뉴스 국제",
      "ts": 1782960237000,
      "pub": "Thu, 2 Jul 2026 11:43:57 +0900",
      "sentiment": "neutral"
    },
    {
      "title": "광주아파트 가격 하락 폭 미세하게 줄어…반도체 특수 주목",
      "link": "https://www.yna.co.kr/view/AKR20260702077800054",
      "source": "연합뉴스 경제",
      "ts": 1782958854000,
      "pub": "Thu, 2 Jul 2026 11:20:54 +0900",
      "sentiment": "neutral"
    },
    {
      "title": "삼성·SK하이닉스·셀트리온 등 충청 첨단산업에 392조 투자",
      "link": "https://www.yna.co.kr/view/AKR20260702034100003",
      "source": "연합뉴스 경제",
      "ts": 1782954674000,
      "pub": "Thu, 2 Jul 2026 10:11:14 +0900",
      "sentiment": "neutral"
    },
    {
      "title": "\"애플, 중국 CXMT·YMTC 칩 구매 협상중…중국내 판매 기기용\"",
      "link": "https://www.yna.co.kr/view/AKR20260702028900009",
      "source": "연합뉴스 국제",
      "ts": 1782950682000,
      "pub": "Thu, 2 Jul 2026 09:04:42 +0900",
      "sentiment": "neutral"
    },
    {
      "title": "뉴욕증시, 반도체주 매도에 약세 마감…마이크론 10% 급락(종합)",
      "link": "https://www.yna.co.kr/view/AKR20260702005551072",
      "source": "연합뉴스 국제",
      "ts": 1782939654000,
      "pub": "Thu, 2 Jul 2026 06:00:54 +0900",
      "sentiment": "negative"
    },
    {
      "title": "뉴욕증시, 반도체주 매도에 약세 마감…마이크론 10% 급락",
      "link": "https://www.yna.co.kr/view/AKR20260702005500072",
      "source": "연합뉴스 국제",
      "ts": 1782936648000,
      "pub": "Thu, 2 Jul 2026 05:10:48 +0900",
      "sentiment": "negative"
    },
    {
      "title": "트럼프 \"마이크론 '트럼프 저축계좌'에 2.5억달러 기여\"",
      "link": "https://www.yna.co.kr/view/AKR20260702002800071",
      "source": "연합뉴스 국제",
      "ts": 1782928837000,
      "pub": "Thu, 2 Jul 2026 03:00:37 +0900",
      "sentiment": "neutral"
    }
  ]
}