{
  "category": "hynix",
  "updated_at": "2026-05-21T23:57:44.627Z",
  "count": 12,
  "items": [
    {
      "title": "협상 초안 합의설? 애플처럼 되는 엔비디아…톰 리 \"스페이스X 상장 부정적\" [김현석의 월스트리트나우]",
      "link": "https://www.hankyung.com/article/202605222997i",
      "source": "한국경제",
      "ts": 1779403694000,
      "pub": "Fri, 22 May 2026 07:48:14 +0900"
    },
    {
      "title": "\"매년 2000억달러 규모 소버린 AI 투자 지속…엔비디아 수혜\"-하나",
      "link": "https://www.hankyung.com/article/2026052231236",
      "source": "한국경제",
      "ts": 1779403143000,
      "pub": "Fri, 22 May 2026 07:39:03 +0900"
    },
    {
      "title": "'中 양대 메모리 굴기' 상장 초읽기…삼성·SK '긴장' 이유는",
      "link": "https://www.hankyung.com/article/202605212187i",
      "source": "한국경제",
      "ts": 1779402603000,
      "pub": "Fri, 22 May 2026 07:30:03 +0900"
    },
    {
      "title": "AMD, 대만 반도체업계에 15조원 투자…엔비디아 추격",
      "link": "https://www.mt.co.kr/world/2026/05/22/2026052206545029826",
      "source": "머니투데이",
      "ts": 1779400634000,
      "pub": "Fri, 22 May 2026 06:57:14 +0900"
    },
    {
      "title": "반도체 호조에 5월 소비심리 석달 만에 반등…11개월내 최대폭↑",
      "link": "https://www.yna.co.kr/view/AKR20260521145800002",
      "source": "연합뉴스 경제",
      "ts": 1779397221000,
      "pub": "Fri, 22 May 2026 06:00:21 +0900"
    },
    {
      "title": "반도체·증시 날개 달자 소비심리도 훨훨…3개월 만에 반등",
      "link": "https://www.mt.co.kr/economy/2026/05/22/2026052116231411309",
      "source": "머니투데이",
      "ts": 1779397200000,
      "pub": "Fri, 22 May 2026 06:00:00 +0900"
    },
    {
      "title": "\"하이닉스부터 예견\" &#039;선 없는 요구&#039; 불씨",
      "link": "https://www.mt.co.kr/industry/2026/05/22/2026052120274683352",
      "source": "머니투데이",
      "ts": 1779391800000,
      "pub": "Fri, 22 May 2026 04:30:00 +0900"
    },
    {
      "title": "AMD, 대만 반도체 생태계에 15조원 투자…엔비디아 추격 시동",
      "link": "https://www.yna.co.kr/view/AKR20260522005700091",
      "source": "연합뉴스 국제",
      "ts": 1779391555000,
      "pub": "Fri, 22 May 2026 04:25:55 +0900"
    },
    {
      "title": "[사설]지방선거 공약대로면 전국이 반도체단지",
      "link": "https://www.mt.co.kr/opinion/2026/05/22/2026052114332229868",
      "source": "머니투데이",
      "ts": 1779390300000,
      "pub": "Fri, 22 May 2026 04:05:00 +0900"
    },
    {
      "title": "美 정부, 양자컴퓨팅 파격 베팅…엔비디아의 진짜 문제 [빈난새의 개장전요것만]",
      "link": "https://www.hankyung.com/article/202605212941i",
      "source": "한국경제",
      "ts": 1779375456000,
      "pub": "Thu, 21 May 2026 23:57:36 +0900"
    },
    {
      "title": "1분기 수출 '톱10' 비중 과반…반도체 업은 대기업 53% 뛰어",
      "link": "https://www.yna.co.kr/view/AKR20260521082800002",
      "source": "연합뉴스 경제",
      "ts": 1779332404000,
      "pub": "Thu, 21 May 2026 12:00:04 +0900"
    },
    {
      "title": "[영상] 삼성전자 성과급 합의…메모리 1인당 6억·적자 사업부 1.6억",
      "link": "https://www.yna.co.kr/view/AKR20260521091900704",
      "source": "연합뉴스 경제",
      "ts": 1779332075000,
      "pub": "Thu, 21 May 2026 11:54:35 +0900"
    }
  ]
}