{
  "category": "intl",
  "updated_at": "2026-05-23T14:47:47.530Z",
  "count": 33,
  "items": [
    {
      "title": "프랑스, '구호선단 활동가 조롱' 이스라엘 장관 입국 금지",
      "link": "https://www.yna.co.kr/view/AKR20260523051200082",
      "source": "연합뉴스 국제",
      "ts": 1779544032000,
      "pub": "Sat, 23 May 2026 22:47:12 +0900"
    },
    {
      "title": "이란 \"전쟁 재개 땐 더 참혹할 것\"…트럼프에 경고 [종합]",
      "link": "https://www.hankyung.com/article/2026052356617",
      "source": "한국경제",
      "ts": 1779540031000,
      "pub": "Sat, 23 May 2026 21:40:31 +0900"
    },
    {
      "title": "백악관 \"트럼프, 대만 무기판매 곧 승인\"…이란전 지연설 부인",
      "link": "https://www.yna.co.kr/view/AKR20260523043900009",
      "source": "연합뉴스 국제",
      "ts": 1779533392000,
      "pub": "Sat, 23 May 2026 19:49:52 +0900"
    },
    {
      "title": "젤렌스키, '우크라에 EU 준회원 지위' 독일 제안에 반발",
      "link": "https://www.yna.co.kr/view/AKR20260523041500108",
      "source": "연합뉴스 국제",
      "ts": 1779524035000,
      "pub": "Sat, 23 May 2026 17:13:55 +0900"
    },
    {
      "title": "\"이스라엘, 며칠 내 美 군사행동 재개 가능성에 대비\"",
      "link": "https://www.yna.co.kr/view/AKR20260523039700108",
      "source": "연합뉴스 국제",
      "ts": 1779523520000,
      "pub": "Sat, 23 May 2026 17:05:20 +0900"
    },
    {
      "title": "트럼프 내각 교체 벌써 네 번째…&#039;핵 문제 이견&#039; 국가정보국장 사임",
      "link": "https://www.mt.co.kr/world/2026/05/23/2026052314405383568",
      "source": "머니투데이",
      "ts": 1779515574000,
      "pub": "Sat, 23 May 2026 14:52:54 +0900"
    },
    {
      "title": "트럼프, 장남 결혼식 돌연 불참…이란 공습 재개 '초긴장'",
      "link": "https://www.hankyung.com/article/2026052354577",
      "source": "한국경제",
      "ts": 1779514594000,
      "pub": "Sat, 23 May 2026 14:36:34 +0900"
    },
    {
      "title": "장남 결혼식 안 가고 연휴 일정 취소...백악관 지키는 트럼프, 이란 공습?",
      "link": "https://www.mt.co.kr/world/2026/05/23/2026052313233925935",
      "source": "머니투데이",
      "ts": 1779511071000,
      "pub": "Sat, 23 May 2026 13:37:51 +0900"
    },
    {
      "title": "\"중국에 진다\"…트럼프 AI규제 멈춰세운 실리콘밸리 경고",
      "link": "https://www.yna.co.kr/view/AKR20260523029800009",
      "source": "연합뉴스 국제",
      "ts": 1779510138000,
      "pub": "Sat, 23 May 2026 13:22:18 +0900"
    },
    {
      "title": "\"성폭행 당하고 전기충격까지\" 가자 구호선 활동가들, 이스라엘군 폭로",
      "link": "https://www.mt.co.kr/world/2026/05/23/2026052312022845015",
      "source": "머니투데이",
      "ts": 1779508187000,
      "pub": "Sat, 23 May 2026 12:49:47 +0900"
    },
    {
      "title": "\"트럼프 딸 이방카도 이란 보복암살 표적이었다\"",
      "link": "https://www.yna.co.kr/view/AKR20260523028400009",
      "source": "연합뉴스 국제",
      "ts": 1779506196000,
      "pub": "Sat, 23 May 2026 12:16:36 +0900"
    },
    {
      "title": "트럼프, 이란 공습재개 저울질…안보회의 후 연휴 개인일정 취소(종합)",
      "link": "https://www.yna.co.kr/view/AKR20260523022451009",
      "source": "연합뉴스 국제",
      "ts": 1779502789000,
      "pub": "Sat, 23 May 2026 11:19:49 +0900"
    },
    {
      "title": "미국 의존 줄인다…EU·멕시코, 상호 관세인하 협정",
      "link": "https://www.yna.co.kr/view/AKR20260523023100009",
      "source": "연합뉴스 국제",
      "ts": 1779499097000,
      "pub": "Sat, 23 May 2026 10:18:17 +0900"
    },
    {
      "title": "트럼프 이란공습 채비…이스라엘 공항에 공중급유기 50여대 집결",
      "link": "https://www.yna.co.kr/view/AKR20260523017300009",
      "source": "연합뉴스 국제",
      "ts": 1779493367000,
      "pub": "Sat, 23 May 2026 08:42:47 +0900"
    },
    {
      "title": "\"이스라엘 구금된 가자 구호선 활동가들 성폭행당했다\"(종합)",
      "link": "https://www.yna.co.kr/view/AKR20260522165951109",
      "source": "연합뉴스 국제",
      "ts": 1779489025000,
      "pub": "Sat, 23 May 2026 07:30:25 +0900"
    },
    {
      "title": "개버드 美국가정보국장 사의…이란위협 저평가로 트럼프에 찍혔나(종합2보)",
      "link": "https://www.yna.co.kr/view/AKR20260523003052071",
      "source": "연합뉴스 국제",
      "ts": 1779488460000,
      "pub": "Sat, 23 May 2026 07:21:00 +0900"
    },
    {
      "title": "美무역대표, 전면적 반도체 관세 \"적절시점에 부과…당장은 없어\"(종합)",
      "link": "https://www.yna.co.kr/view/AKR20260523004551071",
      "source": "연합뉴스 국제",
      "ts": 1779487887000,
      "pub": "Sat, 23 May 2026 07:11:27 +0900"
    },
    {
      "title": "美영주권 신청 까다로워진다…트럼프 정부 \"본국서 신청해야\"(종합)",
      "link": "https://www.yna.co.kr/view/AKR20260523005651071",
      "source": "연합뉴스 국제",
      "ts": 1779485990000,
      "pub": "Sat, 23 May 2026 06:39:50 +0900"
    },
    {
      "title": "트럼프 행정부 \"미국서 하던 영주권 신청 본국 돌아가 해야\"",
      "link": "https://www.yna.co.kr/view/AKR20260523005600071",
      "source": "연합뉴스 국제",
      "ts": 1779478654000,
      "pub": "Sat, 23 May 2026 04:37:34 +0900"
    },
    {
      "title": "트럼프, 장남 결혼식 불참키로…\"중요한 때 백악관에 있어야\"",
      "link": "https://www.yna.co.kr/view/AKR20260523004700071",
      "source": "연합뉴스 국제",
      "ts": 1779476850000,
      "pub": "Sat, 23 May 2026 04:07:30 +0900"
    },
    {
      "title": "美무역대표, 전면적 반도체 관세 \"적절시점에 부과…당장은 없어\"",
      "link": "https://www.yna.co.kr/view/AKR20260523004500071",
      "source": "연합뉴스 국제",
      "ts": 1779476595000,
      "pub": "Sat, 23 May 2026 04:03:15 +0900"
    },
    {
      "title": "'워시의 연준' 트럼프 기대에도 금리인하 단행 어려울듯",
      "link": "https://www.yna.co.kr/view/AKR20260523003700072",
      "source": "연합뉴스 국제",
      "ts": 1779473471000,
      "pub": "Sat, 23 May 2026 03:11:11 +0900"
    },
    {
      "title": "케빈 워시 새 연준 의장 취임…\"개혁지향적인 연준 이끌 것\"(종합2보)",
      "link": "https://www.yna.co.kr/view/AKR20260523001852071",
      "source": "연합뉴스 국제",
      "ts": 1779472631000,
      "pub": "Sat, 23 May 2026 02:57:11 +0900"
    },
    {
      "title": "개버드 美국가정보국장 사의…트럼프 '내각 물갈이' 속도내나",
      "link": "https://www.yna.co.kr/view/AKR20260523003000071",
      "source": "연합뉴스 국제",
      "ts": 1779470700000,
      "pub": "Sat, 23 May 2026 02:25:00 +0900"
    },
    {
      "title": "케빈 워시 연준 의장 취임…\"독립성\" 거론하며 \"개혁 지향\"(종합)",
      "link": "https://www.yna.co.kr/view/AKR20260523001851071",
      "source": "연합뉴스 국제",
      "ts": 1779468740000,
      "pub": "Sat, 23 May 2026 01:52:20 +0900"
    },
    {
      "title": "\"트럼프, 동맹국들에 실망\"…미 국무, 나토 분열 재차 경고(종합)",
      "link": "https://www.yna.co.kr/view/AKR20260523000351098",
      "source": "연합뉴스 국제",
      "ts": 1779467949000,
      "pub": "Sat, 23 May 2026 01:39:09 +0900"
    },
    {
      "title": "케빈 워시 신임 연준 의장 취임…트럼프 \"독립적으로 일하길\"",
      "link": "https://www.yna.co.kr/view/AKR20260523001800071",
      "source": "연합뉴스 국제",
      "ts": 1779466343000,
      "pub": "Sat, 23 May 2026 01:12:23 +0900"
    },
    {
      "title": "[속보] 트럼프, 새 연준 의장 임명식서 \"독립적으로 일하길\"",
      "link": "https://www.yna.co.kr/view/AKR20260523001300071",
      "source": "연합뉴스 국제",
      "ts": 1779465706000,
      "pub": "Sat, 23 May 2026 01:01:46 +0900"
    },
    {
      "title": "\"트럼프행정부, 귀화 미국인 시민권박탈소송 변호사 보강\"",
      "link": "https://www.yna.co.kr/view/AKR20260523000800071",
      "source": "연합뉴스 국제",
      "ts": 1779464774000,
      "pub": "Sat, 23 May 2026 00:46:14 +0900"
    },
    {
      "title": "\"트럼프, 동맹국들에 실망\"…미 국무, 나토 분열 재차 경고",
      "link": "https://www.yna.co.kr/view/AKR20260523000300098",
      "source": "연합뉴스 국제",
      "ts": 1779464205000,
      "pub": "Sat, 23 May 2026 00:36:45 +0900"
    },
    {
      "title": "트럼프, 논란의 '사법피해자기금' 옹호…\"前정권 피해자 지원\"",
      "link": "https://www.yna.co.kr/view/AKR20260522166300071",
      "source": "연합뉴스 국제",
      "ts": 1779460436000,
      "pub": "Fri, 22 May 2026 23:33:56 +0900"
    },
    {
      "title": "트럼프 등쌀에 美 유명 토크쇼 결국 종영…트럼프, 끝까지 독설",
      "link": "https://www.yna.co.kr/view/AKR20260522166000071",
      "source": "연합뉴스 국제",
      "ts": 1779459824000,
      "pub": "Fri, 22 May 2026 23:23:44 +0900"
    },
    {
      "title": "미군 5천명 증파 발표에 폴란드 \"땡큐 트럼프\"(종합)",
      "link": "https://www.yna.co.kr/view/AKR20260522140951082",
      "source": "연합뉴스 국제",
      "ts": 1779459006000,
      "pub": "Fri, 22 May 2026 23:10:06 +0900"
    }
  ]
}