{
  "category": "samsung",
  "updated_at": "2026-06-14T02:56:18.811Z",
  "count": 3,
  "items": [
    {
      "title": "\"삼전닉스 안 부러워요\"…역대급 불장에 '돈방석' 앉은 곳",
      "link": "https://www.hankyung.com/article/2026061447807",
      "source": "한국경제",
      "ts": 1781396378000,
      "pub": "Sun, 14 Jun 2026 09:19:38 +0900",
      "sentiment": "neutral"
    },
    {
      "title": "한경협 회장 \"韓-伊 세계 뻗어가길\"…이재용 \"더 열심히 해야죠\"",
      "link": "https://www.yna.co.kr/view/AKR20260613003800001",
      "source": "연합뉴스 경제",
      "ts": 1781290205000,
      "pub": "Sat, 13 Jun 2026 03:50:05 +0900",
      "sentiment": "neutral"
    },
    {
      "title": "[특징주] 美훈풍에 삼전·닉스↑…'32만전자'·'215만닉스' 회복(종합)",
      "link": "https://www.yna.co.kr/view/AKR20260612041951008",
      "source": "연합뉴스 경제",
      "ts": 1781247586000,
      "pub": "Fri, 12 Jun 2026 15:59:46 +0900",
      "sentiment": "neutral"
    }
  ]
}