{
  "category": "samsung",
  "updated_at": "2026-06-05T12:30:24.170Z",
  "count": 6,
  "items": [
    {
      "title": "'HBM칩' 나눠준 젠슨황…삼겹살에 소주, 노래방 뒤풀이까지 [영상]",
      "link": "https://www.hankyung.com/article/202606050428g",
      "source": "한국경제",
      "ts": 1780658890000,
      "pub": "Fri, 05 Jun 2026 20:28:10 +0900",
      "sentiment": "neutral"
    },
    {
      "title": "삼성전자 '5년간 5兆 사회공헌' 본격 시동",
      "link": "https://www.hankyung.com/article/2026060501411",
      "source": "한국경제",
      "ts": 1780657201000,
      "pub": "Fri, 05 Jun 2026 20:00:01 +0900",
      "sentiment": "neutral"
    },
    {
      "title": "스페이스X로 몰려가는 증시 자금…'삼전닉스' 조정 시작됐나",
      "link": "https://www.hankyung.com/article/2026060502141",
      "source": "한국경제",
      "ts": 1780649855000,
      "pub": "Fri, 05 Jun 2026 17:57:35 +0900",
      "sentiment": "neutral"
    },
    {
      "title": "[특징주] 삼전·닉스, 급락 마감…각각 6%·9%대 하락(종합)",
      "link": "https://www.yna.co.kr/view/AKR20260605034051008",
      "source": "연합뉴스 경제",
      "ts": 1780641648000,
      "pub": "Fri, 5 Jun 2026 15:40:48 +0900",
      "sentiment": "negative"
    },
    {
      "title": "[특징주] 삼전·닉스, 장초반 급락…각각 6%·8%대 하락세",
      "link": "https://www.yna.co.kr/view/AKR20260605034000008",
      "source": "연합뉴스 경제",
      "ts": 1780618927000,
      "pub": "Fri, 5 Jun 2026 09:22:07 +0900",
      "sentiment": "negative"
    },
    {
      "title": "김시우, PGA 투어 메모리얼 토너먼트 1R 공동 23위…임성재 33위",
      "link": "https://www.yna.co.kr/view/AKR20260605022200007",
      "source": "연합뉴스 국제",
      "ts": 1780615651000,
      "pub": "Fri, 5 Jun 2026 08:27:31 +0900",
      "sentiment": "neutral"
    }
  ]
}